Workbook
Name DATA1: 'Vedor Report'!$A$2:$A$9
Name DATA10: 'Vedor Report'!$J$2:$J$9
Name DATA11: 'Vedor Report'!$K$2:$K$9
Name DATA12: 'Vedor Report'!$L$2:$L$9
Name DATA13: 'Vedor Report'!$M$2:$M$9
Name DATA14: 'Vedor Report'!$N$2:$N$9
Name DATA15: 'Vedor Report'!$O$2:$O$9
Name DATA16: 'Vedor Report'!$P$2:$P$9
Name DATA17: 'Vedor Report'!#REF!
Name DATA18: 'Vedor Report'!#REF!
Name DATA19: 'Vedor Report'!#REF!
Name DATA2: 'Vedor Report'!$B$2:$B$9
Name DATA20: 'Vedor Report'!#REF!
Name DATA21: 'Vedor Report'!#REF!
Name DATA22: 'Vedor Report'!$Q$2:$Q$9
Name DATA23: 'Vedor Report'!$R$2:$R$9
Name DATA24: 'Vedor Report'!$S$2:$S$9
Name DATA25: 'Vedor Report'!#REF!
Name DATA26: 'Vedor Report'!$T$2:$T$9
Name DATA27: 'Vedor Report'!$U$2:$U$9
Name DATA28: 'Vedor Report'!$V$2:$V$9
Name DATA29: 'Vedor Report'!$W$2:$W$9
Name DATA3: 'Vedor Report'!$C$2:$C$9
Name DATA30: 'Vedor Report'!$X$2:$X$9
Name DATA31: 'Vedor Report'!$Y$2:$Y$9
Name DATA32: 'Vedor Report'!$Z$2:$Z$9
Name DATA33: 'Vedor Report'!$AA$2:$AA$9
Name DATA34: 'Vedor Report'!#REF!
Name DATA35: 'Vedor Report'!#REF!
Name DATA36: 'Vedor Report'!$AB$2:$AB$9
Name DATA37: 'Vedor Report'!$AC$2:$AC$9
Name DATA38: 'Vedor Report'!$AD$2:$AD$9
Name DATA39: 'Vedor Report'!$AE$2:$AE$9
Name DATA4: 'Vedor Report'!$D$2:$D$9
Name DATA40: 'Vedor Report'!$AF$2:$AF$9
Name DATA41: 'Vedor Report'!$AI$2:$AI$9
Name DATA42: 'Vedor Report'!#REF!
Name DATA43: 'Vedor Report'!#REF!
Name DATA44: 'Vedor Report'!$AJ$2:$AJ$9
Name DATA5: 'Vedor Report'!$E$2:$E$9
Name DATA6: 'Vedor Report'!$F$2:$F$9
Name DATA7: 'Vedor Report'!$G$2:$G$9
Name DATA8: 'Vedor Report'!$H$2:$H$9
Name DATA9: 'Vedor Report'!$I$2:$I$9
Name TEST0: 'Vedor Report'!$A$2:$AJ$9
Name TESTHKEY: 'Vedor Report'!$C$1:$AJ$1
Name TESTKEYS: 'Vedor Report'!$A$2:$B$9
Name TESTVKEY: 'Vedor Report'!$A$1:$B$1

Sheet Vedor Report
A1: Customer ID | B1: DOM/INT | C1: Customer Name | D1: Invoice Number | E1: line Item | F1: Billing Type | G1: Issue Date | H1: Service Type | I1: Service Provider | J1: Service Reference | K1: Description of Service | L1: Supplier Name | M1: Employee ID | N1: Department | O1: Entitlement | P1: PNR No | Q1: Booking Date | R1: Check In Date | S1: Check Out Date | T1: Qty | U1: No of Rooms | V1: No of Nights | W1: T/O Number | X1: Client Name | Y1: Route | Z1: Destination City | AA1: Class/Type | AB1: Total Price W.O VAT | AC1: VAT % | AD1: VAT | AE1: Airline Can Fee | AF1: Total Invoice Amount | AG1: commision amount | AH1: net payable amount | AI1: Currency | AJ1: Booking ID
A2: 2012559 | B2: INT | C2: Qtoon Raqamya Trading Company | D2: 2500054717 | E2: 000001 | F2: Invoice | G2: 46256 | H2: A | I2: FZ | K2: E-Tckt-DS-ONL | N2: QTOON RAQAMYA TRADING COMPANY | P2: 7IGW84 | Q2: 46247 | R2: 08/14/2026 | S2: 08/14/2026 | T2: 1 | W2: 000537832 | X2: MAHENDRA ASARPOTA | Y2: RUH-DXB | AA2: ECONOMY | AB2: 481.38 | AC2: 0 | AD2: 0 | AE2: 0 | AF2: 481.38 | AG2: =IF(AND(LEFT($AJ2)="A",SUM($AB2)>=1),$AB2*0.03,IF(LEFT($AJ2)="H",$AB2*0.05,0))*1.15 -> 16.60761 | AH2: =AF2-AG2 -> 464.77239 | AI2: SAR | AJ2: A260813120395500_5944762 | AK2: A260813120395500
A3: 2012559 | B3: INT | C3: Qtoon Raqamya Trading Company | D3: 2500054717 | E3: 000002 | F3: Invoice | G3: 46256 | H3: A | I3: XY | K3: E-Tckt-DS-ONL | N3: QTOON RAQAMYA TRADING COMPANY | P3: J7G92V | Q3: 46247 | R3: 08/17/2026 | S3: 08/17/2026 | T3: 1 | W3: 000537832 | X3: Asarpota Mahendra | Y3: DXB-RUH | AA3: ECONOMY | AB3: 477.41 | AC3: 0 | AD3: 0 | AE3: 0 | AF3: 477.41 | AG3: =IF(AND(LEFT($AJ3)="A",SUM($AB3)>=1),$AB3*0.03,IF(LEFT($AJ3)="H",$AB3*0.05,0))*1.15 -> 16.470645 | AH3: =AF3-AG3 -> 460.93936 | AI3: SAR | AJ3: A260813120395500_5944762 | AK3: A260813120395500-1
A4: 2012559 | B4: INT | C4: Qtoon Raqamya Trading Company | D4: 2500054633 | E4: 000001 | F4: Invoice | G4: 46251 | H4: A | I4: RJ | J4: 4861440457 | K4: E-Tckt-DS-ONL | N4: QTOON RAQAMYA TRADING COMPANY | P4: 7IDXN4 | Q4: 46251 | R4: 08/17/2026 | S4: 08/17/2026 | T4: 1 | W4: 000539591 | X4: HUSAIN ALI | Y4: AMM-DMM | AA4: Q | AB4: 1324.08 | AC4: 0 | AD4: 0 | AE4: 0 | AF4: 1324.08 | AG4: =IF(AND(LEFT($AJ4)="A",SUM($AB4)>=1),$AB4*0.03,IF(LEFT($AJ4)="H",$AB4*0.05,0))*1.15 -> 45.68076 | AH4: =AF4-AG4 -> 1278.3992 | AI4: SAR | AJ4: A26081760435500_4482019 | AK4: A26081760435500
A5: 2012559 | B5: DOM | C5: Qtoon Raqamya Trading Company | D5: 2500054676 | E5: 000001 | F5: Invoice | G5: 46251 | H5: A | I5: F3 | K5: E-Tckt-DS-ONL | N5: QTOON RAQAMYA TRADING COMPANY | P5: W6S2MS | Q5: 46251 | R5: 08/23/2026 | S5: 08/23/2026 | T5: 1 | W5: 000539882 | X5: MR Abdullah Aloufi | Y5: AHB-JED | AA5: ECONOMY | AB5: 384.38 | AC5: 15 | AD5: 57.66 | AE5: 0 | AF5: 442.04 | AG5: =IF(AND(LEFT($AJ5)="A",SUM($AB5)>=1),$AB5*0.03,IF(LEFT($AJ5)="H",$AB5*0.05,0))*1.15 -> 13.26111 | AH5: =AF5-AG5 -> 428.77889 | AI5: SAR | AJ5: A260817163765500_865574 | AK5: A260817163765500
A6: 2012559 | B6: INT | C6: Qtoon Raqamya Trading Company | D6: 2500054685 | E6: 000001 | F6: Invoice | G6: 46253 | H6: H | I6: HOTEL ORSO BRUNO | J6: 2538409917 | K6: Online-Accomodations | L6: EXPEDIA | N6: QTOON RAQAMYA TRADING COMPANY | Q6: 46253 | R6: 09/19/2026 | S6: 09/20/2026 | T6: 1 | U6: 1 | V6: 1 | W6: H260819107345500 | X6: Salah Faqihi | Z6: CARATE URIO | AA6: STANDARD ONE-BEDROOM ROOM - 2 | AB6: 1162.76 | AC6: 0 | AD6: 0 | AE6: 0 | AF6: 1162.76 | AG6: =IF(AND(LEFT($AJ6)="A",SUM($AB6)>=1),$AB6*0.03,IF(LEFT($AJ6)="H",$AB6*0.05,0))*1.15 -> 66.8587 | AH6: =AF6-AG6 -> 1095.9013 | AI6: SAR | AJ6: H260819107345500_3360174 | AK6: H260819107345500
A7: 2012559 | B7: INT | C7: Qtoon Raqamya Trading Company | D7: 2500054677 | E7: 000001 | F7: Invoice | G7: 46254 | H7: A | I7: XY | K7: E-Tckt-DS-ONL | N7: QTOON RAQAMYA TRADING COMPANY | P7: GICBFE | Q7: 46254 | R7: 08/30/2026 | S7: 08/30/2026 | T7: 1 | W7: 000541488 | X7: Baharithah Meshari | Y7: RUH-BJV | AA7: ECONOMY | AB7: 754.27 | AC7: 0 | AD7: 0 | AE7: 0 | AF7: 754.27 | AG7: =IF(AND(LEFT($AJ7)="A",SUM($AB7)>=1),$AB7*0.03,IF(LEFT($AJ7)="H",$AB7*0.05,0))*1.15 -> 26.022315 | AH7: =AF7-AG7 -> 728.24768 | AI7: SAR | AJ7: A26082095495500_8209175 | AK7: A26082095495500
A8: 2012559 | B8: DOM | C8: Qtoon Raqamya Trading Company | D8: 2500054678 | E8: 000001 | F8: Invoice | G8: 46254 | H8: A | I8: XY | K8: E-Tckt-DS-ONL | N8: QTOON RAQAMYA TRADING COMPANY | P8: ZI84FX | Q8: 46254 | R8: 08/26/2026 | S8: 08/30/2026 | T8: 1 | W8: 000541686 | Y8: AJF-RUH-JED-RUH-AJF | AA8: ECONOMY | AB8: 1224.43 | AC8: 15 | AD8: 183.67 | AE8: 0 | AF8: 1408.1 | AG8: =IF(AND(LEFT($AJ8)="A",SUM($AB8)>=1),$AB8*0.03,IF(LEFT($AJ8)="H",$AB8*0.05,0))*1.15 -> 42.242835 | AH8: =AF8-AG8 -> 1365.8572 | AI8: SAR | AJ8: A260820198585500_841607 | AK8: A260820198585500
A9: 2012559 | B9: DOM | C9: Qtoon Raqamya Trading Company | D9: 2500054679 | E9: 000001 | F9: Invoice | G9: 46255 | H9: A | I9: F3 | K9: E-Tckt-DS-ONL | N9: QTOON RAQAMYA TRADING COMPANY | P9: FB8Q9A | Q9: 46255 | R9: 09/04/2026 | S9: 09/04/2026 | T9: 1 | W9: 000541882 | X9: MS Jacqueline Ndayizeye MS S | Y9: ABT-RUH | AA9: ECONOMY | AB9: 813.15 | AC9: 15 | AD9: 121.97 | AE9: 0 | AF9: 935.12 | AG9: =IF(AND(LEFT($AJ9)="A",SUM($AB9)>=1),$AB9*0.03,IF(LEFT($AJ9)="H",$AB9*0.05,0))*1.15 -> 28.053675 | AH9: =AF9-AG9 -> 907.06633 | AI9: SAR | AJ9: A26082185665500_7471325 | AK9: A26082185665500
AF10: =SUM(DATA40) -> 6985.16 | AG10: =SUM(AG2:AG9) -> 255.19765 | AH10: =SUM(AH2:AH9) -> 6729.9623

Sheet Sheet2
A1: Claim period | B1: Total Claim | C1: Commision invoices Amount | D1: total Payable amount | E1: Paid Amount | F1: DIFF in payment | G1: unprovided Commision invoices
A2: Claim From 21 till 27 Jun 2026 | B2: 1739.96 | C2: 63.13 | D2: =B2-C2 -> 1676.83 | E2: 0 | F2: =D2 -> 1676.83
A3: claim From 09 till 15 AUG 2026 | B3: 9334.87 | C3: 298.66771 | D3: =B3-C3 -> 9036.2023 | F3: =D3 -> 9036.2023 | G3: =C3 -> 298.66771
A4: claim From 16 till 22 AUG 2026 | B4: 6985.16 | C4: 255.19765 | D4: =B4-C4 -> 6729.9624 | F4: =D4 -> 6729.9624 | G4: =C4 -> 255.19765
B5: =SUM(B2:B4) -> 18059.99 | C5: =SUM(C2:C4) -> 616.99536 | D5: =SUM(D2:D4) -> 17442.995 | E5: =SUM(E2:E3) -> 0 | F5: =SUM(F2:F4) -> 17442.995 | G5: =SUM(G3:G4) -> 553.86536

Sheet Hotel
A1: Order Date | B1: Order Time | C1: Customer | D1: Customer | E1: Customer | F1: SG Order ID | G1: Partner Order ID | H1: Vertical | I1: Provider Name | J1: Food Order Type | K1: Restaurant ID/Seller ID | L1: Restaurant Name | M1: Transaction ID | N1: Order Status | O1: Payment Status | P1: Payment Method | Q1: Sub Total | R1: Promocode | S1: SG Discount/Promo Amount | T1: SG Delivery Expense | U1: VAT | V1: Order Total | W1: Total Amount | X1: Vendor Delivery Expense | Y1: SG Comission % | Z1: Commission Amount | AA1: Partner Payout | AB1: Margin | AC1: Vendor Payment Term | AD1: SG Earnings (before VAT) | AE1: VAT on SG Earnings | AF1: SG Earning (including VAT) | AG1: Wallet Amount | AH1: Applepay/Card Amount | AI1: Commission Charged | AJ1: Refund Amount | AK1: Compensation Amount | AL1: Net Payable Amount to Partner
A2: 46254 | B2: 06:08 PM | C2: 45841 | F2: 124 | G2: - | H2: Hotel | I2: Almosafer | J2: - | K2: - | L2: - | M2: ba9ddbb3-5dc6-4694-bf6e-d9ea508c2973 | N2: Pending | O2: Pending | P2: Tamara | Q2: 226.45 | R2: - | S2: - | T2: - | U2: 0 | V2: 226.45 | W2: 226.45 | X2: - | Y2: - | Z2: 0 | AA2: 0 | AB2: 0 | AC2: - | AD2: 0 | AE2: 0 | AF2: 0 | AG2: 0 | AH2: 226.45 | AI2: 0 | AJ2: 0 | AK2: - | AL2: 226.45
A3: 46254 | B3: 05:27 PM | C3: 62725 | F3: 123 | G3: - | H3: Hotel | I3: Almosafer | J3: - | K3: - | L3: - | M3: - | N3: Expired | O3: - | P3: Card | Q3: 125.61 | R3: - | S3: - | T3: - | U3: 16.38 | V3: 125.61 | W3: 125.61 | X3: - | Y3: - | Z3: 0 | AA3: 0 | AB3: 0 | AC3: - | AD3: 0 | AE3: 0 | AF3: 0 | AG3: 0 | AH3: 125.61 | AI3: 0 | AJ3: 0 | AK3: - | AL3: 125.61
A4: 46254 | B4: 01:17 AM | C4: 64510 | F4: 122 | G4: - | H4: Hotel | I4: Almosafer | J4: - | K4: - | L4: - | M4: - | N4: Pending | O4: - | P4: Card | Q4: 7056.88 | R4: - | S4: - | T4: - | U4: 0 | V4: 7056.88 | W4: 7056.88 | X4: - | Y4: - | Z4: 0 | AA4: 0 | AB4: 0 | AC4: - | AD4: 0 | AE4: 0 | AF4: 0 | AG4: 0 | AH4: 7056.88 | AI4: 0 | AJ4: 0 | AK4: - | AL4: 7056.88
A5: 46253 | B5: 06:01 PM | C5: 51981 | D5: حسن فقيه | F5: 121 | G5: H260819107345500 | H5: Hotel | I5: Almosafer | J5: - | K5: - | L5: - | M5: tok_gxrunyib3gpyncel75lr6e7cgu | N5: Processed | O5: Completed | P5: Apple Pay | Q5: 1161.7 | R5: - | S5: - | T5: - | U5: 0 | V5: 1161.7 | W5: 1161.7 | X5: - | Y5: - | Z5: 0 | AA5: 1103.62 | AB5: 0 | AC5: - | AD5: 0 | AE5: 58.09 | AF5: 0 | AG5: 0 | AH5: 1161.7 | AI5: 58.09 | AJ5: 0 | AK5: - | AL5: 1103.61
A6: 46252 | B6: 05:11 PM | C6: 48424 | F6: 120 | G6: - | H6: Hotel | I6: Almosafer | J6: - | K6: - | L6: - | M6: - | N6: Expired | O6: - | P6: Card | Q6: 449 | R6: - | S6: - | T6: - | U6: 0 | V6: 449 | W6: 449 | X6: - | Y6: - | Z6: 0 | AA6: 0 | AB6: 0 | AC6: - | AD6: 0 | AE6: 0 | AF6: 0 | AG6: 0 | AH6: 449 | AI6: 0 | AJ6: 0 | AK6: - | AL6: 449

Sheet Flight
A1: Order Date | B1: Order Time | C1: Customer | D1: Customer | E1: Customer | F1: SG Order ID | G1: Partner Order ID | H1: Vertical | I1: Provider Name | J1: Food Order Type | K1: Restaurant ID/Seller ID | L1: Restaurant Name | M1: Transaction ID | N1: Order Status | O1: Payment Status | P1: Payment Method | Q1: Sub Total | R1: Promocode | S1: SG Discount/Promo Amount | T1: SG Delivery Expense | U1: VAT | V1: Order Total | W1: Total Amount | X1: Vendor Delivery Expense | Y1: SG Comission % | Z1: Commission Amount | AA1: Partner Payout | AB1: Margin | AC1: Vendor Payment Term | AD1: SG Earnings (before VAT) | AE1: VAT on SG Earnings | AF1: SG Earning (including VAT) | AG1: Wallet Amount | AH1: Applepay/Card Amount | AI1: Commission Charged | AJ1: Refund Amount | AK1: Compensation Amount | AL1: Net Payable Amount to Partner
A2: 46256 | B2: 08:56 PM | C2: 53336 | F2: 372 | G2: - | H2: Flights | I2: Almosafer | J2: - | K2: - | L2: - | M2: 5616311e-3e5f-40e2-b0f5-5d105f18ebde | N2: Pending | O2: Pending | P2: Tamara | Q2: 1833.24 | R2: - | S2: - | T2: - | U2: 0 | V2: 1833.24 | W2: 1833.24 | X2: - | Y2: - | Z2: 55 | AA2: - | AB2: 55 | AC2: - | AD2: 0 | AE2: 55 | AF2: 55 | AG2: - | AH2: 1833.24 | AI2: 55 | AJ2: - | AK2: - | AL2: 1778.24
A3: 46256 | B3: 08:53 PM | C3: 53336 | F3: 371 | G3: - | H3: Flights | I3: Almosafer | J3: - | K3: - | L3: - | M3: b491faeb-0409-4573-9d33-6626c9bb2798 | N3: Expired | O3: Pending | P3: Tamara | Q3: 1336.23 | R3: - | S3: - | T3: - | U3: 0 | V3: 1336.23 | W3: 1336.23 | X3: - | Y3: - | Z3: 40.09 | AA3: - | AB3: 40.09 | AC3: - | AD3: 0 | AE3: 40.09 | AF3: 40.09 | AG3: - | AH3: 1336.23 | AI3: 40.09 | AJ3: - | AK3: - | AL3: 1296.14
A4: 46256 | B4: 07:30 PM | C4: 53336 | F4: 370 | G4: - | H4: Flights | I4: Almosafer | J4: - | K4: - | L4: - | M4: cadffe03-4a11-4790-95b6-92fd8163c2fc | N4: Expired | O4: Pending | P4: Tamara | Q4: 2227.06 | R4: - | S4: - | T4: - | U4: 0 | V4: 2227.06 | W4: 2227.06 | X4: - | Y4: - | Z4: 66.81 | AA4: - | AB4: 66.81 | AC4: - | AD4: 0 | AE4: 66.81 | AF4: 66.81 | AG4: - | AH4: 2227.06 | AI4: 66.81 | AJ4: - | AK4: - | AL4: 2160.25
A5: 46256 | B5: 07:30 PM | C5: 53336 | F5: 369 | G5: - | H5: Flights | I5: Almosafer | J5: - | K5: - | L5: - | M5: cadffe03-4a11-4790-95b6-92fd8163c2fc | N5: Expired | O5: Pending | P5: Tamara | Q5: 2227.06 | R5: - | S5: - | T5: - | U5: 0 | V5: 2227.06 | W5: 2227.06 | X5: - | Y5: - | Z5: 66.81 | AA5: - | AB5: 66.81 | AC5: - | AD5: 0 | AE5: 66.81 | AF5: 66.81 | AG5: - | AH5: 2227.06 | AI5: 66.81 | AJ5: - | AK5: - | AL5: 2160.25
A6: 46256 | B6: 07:21 PM | C6: 53336 | F6: 368 | G6: - | H6: Flights | I6: Almosafer | J6: - | K6: - | L6: - | M6: 74196a95-7a17-41da-8fe8-97a2d75a6464 | N6: Expired | O6: Pending | P6: Tamara | Q6: 3180.14 | R6: - | S6: - | T6: - | U6: 0 | V6: 3180.14 | W6: 3180.14 | X6: - | Y6: - | Z6: 95.4 | AA6: - | AB6: 95.4 | AC6: - | AD6: 0 | AE6: 95.4 | AF6: 95.4 | AG6: - | AH6: 3180.14 | AI6: 95.4 | AJ6: - | AK6: - | AL6: 3084.74
A7: 46256 | B7: 07:21 PM | C7: 53336 | F7: 367 | G7: - | H7: Flights | I7: Almosafer | J7: - | K7: - | L7: - | M7: 74196a95-7a17-41da-8fe8-97a2d75a6464 | N7: Expired | O7: Pending | P7: Tamara | Q7: 3180.14 | R7: - | S7: - | T7: - | U7: 0 | V7: 3180.14 | W7: 3180.14 | X7: - | Y7: - | Z7: 95.4 | AA7: - | AB7: 95.4 | AC7: - | AD7: 0 | AE7: 95.4 | AF7: 95.4 | AG7: - | AH7: 3180.14 | AI7: 95.4 | AJ7: - | AK7: - | AL7: 3084.74
A8: 46256 | B8: 02:09 PM | C8: 52182 | F8: 366 | G8: - | H8: Flights | I8: Almosafer | J8: - | K8: - | L8: - | M8: - | N8: Pending | O8: - | P8: Card | Q8: 1379.08 | R8: - | S8: - | T8: - | U8: 0 | V8: 1379.08 | W8: 1379.08 | X8: - | Y8: - | Z8: 41.37 | AA8: - | AB8: 41.37 | AC8: - | AD8: 0 | AE8: 41.37 | AF8: 41.37 | AG8: - | AH8: 1379.08 | AI8: 41.37 | AJ8: - | AK8: - | AL8: 1337.71
A9: 46256 | B9: 02:09 PM | C9: 52182 | F9: 365 | G9: - | H9: Flights | I9: Almosafer | J9: - | K9: - | L9: - | M9: - | N9: Pending | O9: - | P9: Card | Q9: 1379.08 | R9: - | S9: - | T9: - | U9: 0 | V9: 1379.08 | W9: 1379.08 | X9: - | Y9: - | Z9: 41.37 | AA9: - | AB9: 41.37 | AC9: - | AD9: 0 | AE9: 41.37 | AF9: 41.37 | AG9: - | AH9: 1379.08 | AI9: 41.37 | AJ9: - | AK9: - | AL9: 1337.71
A10: 46255 | B10: 06:22 PM | C10: 7435 | F10: 364 | G10: A26082185665500 | H10: Flights | I10: Almosafer | J10: - | K10: - | L10: - | M10: tok_gzzmucybmmvibgbnwp7b4xbppa | N10: Processed | O10: Paid | P10: Apple Pay | Q10: 935.12 | R10: - | S10: - | T10: - | U10: 121.97 | V10: 935.12 | W10: 935.12 | X10: - | Y10: - | Z10: 28.05 | AA10: - | AB10: 28.05 | AC10: - | AD10: 0 | AE10: 28.05 | AF10: 28.05 | AG10: - | AH10: 935.12 | AI10: 28.05 | AJ10: - | AK10: - | AL10: 907.07
A11: 46255 | B11: 05:07 PM | C11: 45760 | F11: 363 | G11: - | H11: Flights | I11: Almosafer | J11: - | K11: - | L11: - | M11: - | N11: Expired | O11: - | P11: Card | Q11: 297.51 | R11: - | S11: - | T11: - | U11: 0 | V11: 297.51 | W11: 297.51 | X11: - | Y11: - | Z11: 8.93 | AA11: - | AB11: 8.93 | AC11: - | AD11: 0 | AE11: 8.93 | AF11: 8.93 | AG11: - | AH11: 297.51 | AI11: 8.93 | AJ11: - | AK11: - | AL11: 288.58
A12: 46255 | B12: 01:34 AM | C12: 52652 | F12: 362 | G12: A260820198585500 | H12: Flights | I12: Almosafer | J12: - | K12: - | L12: - | M12: tok_w7c6oeabckky3p5j6ltbesrcdu | N12: Processed | O12: Paid | P12: Apple Pay + Wallet | Q12: 1408.1 | R12: - | S12: - | T12: - | U12: 183.67 | V12: 1408.1 | W12: 1408.1 | X12: - | Y12: - | Z12: 42.24 | AA12: - | AB12: 42.24 | AC12: - | AD12: 0 | AE12: 42.24 | AF12: 42.24 | AG12: 2 | AH12: 1406.1 | AI12: 42.24 | AJ12: - | AK12: - | AL12: 1365.86
A13: 46255 | B13: 01:34 AM | C13: 52652 | F13: 361 | G13: A260820198585500 | H13: Flights | I13: Almosafer | J13: - | K13: - | L13: - | M13: tok_w7c6oeabckky3p5j6ltbesrcdu | N13: Processed | O13: Paid | P13: Apple Pay + Wallet | Q13: 1408.1 | R13: - | S13: - | T13: - | U13: 183.67 | V13: 1408.1 | W13: 1408.1 | X13: - | Y13: - | Z13: 42.24 | AA13: - | AB13: 42.24 | AC13: - | AD13: 0 | AE13: 42.24 | AF13: 42.24 | AG13: 2 | AH13: 1406.1 | AI13: 42.24 | AJ13: - | AK13: - | AL13: 1365.86
A14: 46254 | B14: 04:41 PM | C14: 53917 | F14: 360 | G14: A26082095495500 | H14: Flights | I14: Almosafer | J14: - | K14: - | L14: - | M14: - | N14: Processed | O14: Paid | P14: Wallet | Q14: 754.27 | R14: - | S14: - | T14: - | U14: 0 | V14: 754.27 | W14: 754.27 | X14: - | Y14: - | Z14: 22.63 | AA14: - | AB14: 22.63 | AC14: - | AD14: 0 | AE14: 22.63 | AF14: 22.63 | AG14: 754.27 | AH14: - | AI14: 22.63 | AJ14: - | AK14: - | AL14: 731.64
A15: 46254 | B15: 01:15 PM | C15: 51918 | F15: 359 | G15: - | H15: Flights | I15: Almosafer | J15: - | K15: - | L15: - | M15: - | N15: Expired | O15: - | P15: Card | Q15: 420.95 | R15: - | S15: - | T15: - | U15: 54.91 | V15: 420.95 | W15: 420.95 | X15: - | Y15: - | Z15: 12.63 | AA15: - | AB15: 12.63 | AC15: - | AD15: 0 | AE15: 12.63 | AF15: 12.63 | AG15: - | AH15: 420.95 | AI15: 12.63 | AJ15: - | AK15: - | AL15: 408.32
A16: 46254 | B16: 01:13 PM | C16: 8003 | D16: mahendra Asar | F16: 357 | G16: - | H16: Flights | I16: Almosafer | J16: - | K16: - | L16: - | M16: - | N16: Expired | O16: - | P16: Card | Q16: 958.32 | R16: - | S16: - | T16: - | U16: 0 | V16: 958.32 | W16: 958.32 | X16: - | Y16: - | Z16: 28.75 | AA16: - | AB16: 28.75 | AC16: - | AD16: 0 | AE16: 28.75 | AF16: 28.75 | AG16: - | AH16: 958.32 | AI16: 28.75 | AJ16: - | AK16: - | AL16: 929.57
A17: 46254 | B17: 01:13 PM | C17: 8003 | D17: mahendra Asar | F17: 358 | G17: - | H17: Flights | I17: Almosafer | J17: - | K17: - | L17: - | M17: - | N17: Expired | O17: - | P17: Card | Q17: 958.32 | R17: - | S17: - | T17: - | U17: 0 | V17: 958.32 | W17: 958.32 | X17: - | Y17: - | Z17: 28.75 | AA17: - | AB17: 28.75 | AC17: - | AD17: 0 | AE17: 28.75 | AF17: 28.75 | AG17: - | AH17: 958.32 | AI17: 28.75 | AJ17: - | AK17: - | AL17: 929.57
A18: 46254 | B18: 01:10 PM | C18: 51918 | F18: 356 | G18: - | H18: Flights | I18: Almosafer | J18: - | K18: - | L18: - | M18: - | N18: Expired | O18: - | P18: Card | Q18: 336.55 | R18: - | S18: - | T18: - | U18: 43.9 | V18: 336.55 | W18: 336.55 | X18: - | Y18: - | Z18: 10.1 | AA18: - | AB18: 10.1 | AC18: - | AD18: 0 | AE18: 10.1 | AF18: 10.1 | AG18: - | AH18: 336.55 | AI18: 10.1 | AJ18: - | AK18: - | AL18: 326.45
A19: 46254 | B19: 06:51 AM | C19: 22768 | D19: احمد محمد | F19: 355 | G19: - | H19: Flights | I19: Almosafer | J19: - | K19: - | L19: - | M19: 321beac8-4e68-418d-9a21-1960aec2efcb | N19: Pending | O19: Pending | P19: Tamara | Q19: 4949.79 | R19: - | S19: - | T19: - | U19: 0 | V19: 4949.79 | W19: 4949.79 | X19: - | Y19: - | Z19: 148.49 | AA19: - | AB19: 148.49 | AC19: - | AD19: 0 | AE19: 148.49 | AF19: 148.49 | AG19: - | AH19: 4949.79 | AI19: 148.49 | AJ19: - | AK19: - | AL19: 4801.3
A20: 46254 | B20: 06:51 AM | C20: 22768 | D20: احمد محمد | F20: 354 | G20: - | H20: Flights | I20: Almosafer | J20: - | K20: - | L20: - | M20: 321beac8-4e68-418d-9a21-1960aec2efcb | N20: Pending | O20: Pending | P20: Tamara | Q20: 4949.79 | R20: - | S20: - | T20: - | U20: 0 | V20: 4949.79 | W20: 4949.79 | X20: - | Y20: - | Z20: 148.49 | AA20: - | AB20: 148.49 | AC20: - | AD20: 0 | AE20: 148.49 | AF20: 148.49 | AG20: - | AH20: 4949.79 | AI20: 148.49 | AJ20: - | AK20: - | AL20: 4801.3
A21: 46254 | B21: 02:58 AM | C21: 53601 | F21: 353 | G21: - | H21: Flights | I21: Almosafer | J21: - | K21: - | L21: - | M21: - | N21: Expired | O21: Failed | P21: Card | Q21: 2579.43 | R21: - | S21: - | T21: - | U21: 0 | V21: 2579.43 | W21: 2579.43 | X21: - | Y21: - | Z21: 77.38 | AA21: - | AB21: 77.38 | AC21: - | AD21: 0 | AE21: 77.38 | AF21: 77.38 | AG21: - | AH21: 2579.43 | AI21: 77.38 | AJ21: - | AK21: - | AL21: 2502.05
A22: 46254 | B22: 02:53 AM | C22: 53601 | F22: 352 | G22: - | H22: Flights | I22: Almosafer | J22: - | K22: - | L22: - | M22: - | N22: Expired | O22: - | P22: Card | Q22: 2579.43 | R22: - | S22: - | T22: - | U22: 0 | V22: 2579.43 | W22: 2579.43 | X22: - | Y22: - | Z22: 77.38 | AA22: - | AB22: 77.38 | AC22: - | AD22: 0 | AE22: 77.38 | AF22: 77.38 | AG22: - | AH22: 2579.43 | AI22: 77.38 | AJ22: - | AK22: - | AL22: 2502.05
A23: 46254 | B23: 02:36 AM | C23: 53601 | F23: 351 | G23: - | H23: Flights | I23: Almosafer | J23: - | K23: - | L23: - | M23: - | N23: Expired | O23: - | P23: Card | Q23: 2962.83 | R23: - | S23: - | T23: - | U23: 0 | V23: 2962.83 | W23: 2962.83 | X23: - | Y23: - | Z23: 88.88 | AA23: - | AB23: 88.88 | AC23: - | AD23: 0 | AE23: 88.88 | AF23: 88.88 | AG23: - | AH23: 2962.83 | AI23: 88.88 | AJ23: - | AK23: - | AL23: 2873.95
A24: 46253 | B24: 08:26 PM | C24: 53917 | F24: 350 | G24: - | H24: Flights | I24: Almosafer | J24: - | K24: - | L24: - | M24: tok_hhalz2yb3efirag3ocvwhnzlvm | N24: Expired | O24: Refunded | P24: Apple Pay + Wallet | Q24: 754.27 | R24: - | S24: - | T24: - | U24: 0 | V24: 754.27 | W24: 754.27 | X24: - | Y24: - | Z24: 22.63 | AA24: - | AB24: 22.63 | AC24: - | AD24: 0 | AE24: 22.63 | AF24: 22.63 | AG24: 5 | AH24: 749.27 | AI24: 22.63 | AJ24: - | AK24: - | AL24: 731.64
A25: 46252 | B25: 11:17 PM | C25: 52320 | F25: 349 | G25: - | H25: Flights | I25: Almosafer | J25: - | K25: - | L25: - | M25: - | N25: Pending | O25: - | P25: Card | Q25: 849.97 | R25: - | S25: - | T25: - | U25: 0 | V25: 849.97 | W25: 849.97 | X25: - | Y25: - | Z25: 25.5 | AA25: - | AB25: 25.5 | AC25: - | AD25: 0 | AE25: 25.5 | AF25: 25.5 | AG25: - | AH25: 849.97 | AI25: 25.5 | AJ25: - | AK25: - | AL25: 824.47
A26: 46252 | B26: 11:17 PM | C26: 52320 | F26: 348 | G26: - | H26: Flights | I26: Almosafer | J26: - | K26: - | L26: - | M26: - | N26: Pending | O26: - | P26: Card | Q26: 849.97 | R26: - | S26: - | T26: - | U26: 0 | V26: 849.97 | W26: 849.97 | X26: - | Y26: - | Z26: 25.5 | AA26: - | AB26: 25.5 | AC26: - | AD26: 0 | AE26: 25.5 | AF26: 25.5 | AG26: - | AH26: 849.97 | AI26: 25.5 | AJ26: - | AK26: - | AL26: 824.47
A27: 46252 | B27: 05:28 PM | C27: 54133 | F27: 347 | G27: - | H27: Flights | I27: Almosafer | J27: - | K27: - | L27: - | M27: - | N27: Expired | O27: - | P27: Card | Q27: 345.32 | R27: - | S27: - | T27: - | U27: 45.04 | V27: 345.32 | W27: 345.32 | X27: - | Y27: - | Z27: 10.36 | AA27: - | AB27: 10.36 | AC27: - | AD27: 0 | AE27: 10.36 | AF27: 10.36 | AG27: - | AH27: 345.32 | AI27: 10.36 | AJ27: - | AK27: - | AL27: 334.96
A28: 46252 | B28: 09:18 AM | C28: 43099 | F28: 346 | G28: - | H28: Flights | I28: Almosafer | J28: - | K28: - | L28: - | M28: - | N28: Expired | O28: - | P28: Card | Q28: 358.07 | R28: - | S28: - | T28: - | U28: 0 | V28: 358.07 | W28: 358.07 | X28: - | Y28: - | Z28: 10.74 | AA28: - | AB28: 10.74 | AC28: - | AD28: 0 | AE28: 10.74 | AF28: 10.74 | AG28: - | AH28: 358.07 | AI28: 10.74 | AJ28: - | AK28: - | AL28: 347.33
A29: 46252 | B29: 12:19 AM | C29: 53917 | F29: 345 | G29: - | H29: Flights | I29: Almosafer | J29: - | K29: - | L29: - | M29: 635e6021-b87b-45f7-8a13-9551aa75b7e0 | N29: Expired | O29: Pending | P29: Tamara | Q29: 754.27 | R29: - | S29: - | T29: - | U29: 0 | V29: 754.27 | W29: 754.27 | X29: - | Y29: - | Z29: 22.63 | AA29: - | AB29: 22.63 | AC29: - | AD29: 0 | AE29: 22.63 | AF29: 22.63 | AG29: - | AH29: 754.27 | AI29: 22.63 | AJ29: - | AK29: - | AL29: 731.64
A30: 46251 | B30: 10:28 PM | C30: 54062 | F30: 344 | G30: A260817163765500 | H30: Flights | I30: Almosafer | J30: - | K30: - | L30: - | M30: tok_g5vf2sibjwvi5pjmeasnbhqqkq | N30: Processed | O30: Paid | P30: Apple Pay | Q30: 442.04 | R30: - | S30: - | T30: - | U30: 57.66 | V30: 442.04 | W30: 442.04 | X30: - | Y30: - | Z30: 13.26 | AA30: - | AB30: 13.26 | AC30: - | AD30: 0 | AE30: 13.26 | AF30: 13.26 | AG30: - | AH30: 442.04 | AI30: 13.26 | AJ30: - | AK30: - | AL30: 428.78
A31: 46251 | B31: 03:04 PM | C31: 54012 | F31: 343 | G31: - | H31: Flights | I31: Almosafer | J31: - | K31: - | L31: - | M31: - | N31: Expired | O31: - | P31: Card | Q31: 455.76 | R31: - | S31: - | T31: - | U31: 0 | V31: 455.76 | W31: 455.76 | X31: - | Y31: - | Z31: 13.67 | AA31: - | AB31: 13.67 | AC31: - | AD31: 0 | AE31: 13.67 | AF31: 13.67 | AG31: - | AH31: 455.76 | AI31: 13.67 | AJ31: - | AK31: - | AL31: 442.09
A32: 46251 | B32: 02:08 PM | C32: 22 | D32: ss alsalloom | F32: 342 | G32: A26081760435500 | H32: Flights | I32: Almosafer | J32: - | K32: - | L32: - | M32: pay_xtpephabc4lidld5agyqqyr2pq | N32: Processed | O32: Paid | P32: Card + Wallet | Q32: 1324.08 | R32: - | S32: - | T32: - | U32: 0 | V32: 1324.08 | W32: 1324.08 | X32: - | Y32: - | Z32: 39.72 | AA32: - | AB32: 39.72 | AC32: - | AD32: 0 | AE32: 39.72 | AF32: 39.72 | AG32: 30 | AH32: 1294.08 | AI32: 39.72 | AJ32: - | AK32: - | AL32: 1284.36
A33: 46250 | B33: 11:07 PM | C33: 46008 | F33: 340 | G33: - | H33: Flights | I33: Almosafer | J33: - | K33: - | L33: - | M33: e213c370-d0fa-4de0-aede-e78699e6ae40 | N33: Expired | O33: Pending | P33: Tamara | Q33: 962.85 | R33: - | S33: - | T33: - | U33: 0 | V33: 962.85 | W33: 962.85 | X33: - | Y33: - | Z33: 28.89 | AA33: - | AB33: 28.89 | AC33: - | AD33: 0 | AE33: 28.89 | AF33: 28.89 | AG33: - | AH33: 962.85 | AI33: 28.89 | AJ33: - | AK33: - | AL33: 933.96
A34: 46250 | B34: 11:07 PM | C34: 46008 | F34: 341 | G34: - | H34: Flights | I34: Almosafer | J34: - | K34: - | L34: - | M34: e213c370-d0fa-4de0-aede-e78699e6ae40 | N34: Expired | O34: Pending | P34: Tamara | Q34: 962.85 | R34: - | S34: - | T34: - | U34: 0 | V34: 962.85 | W34: 962.85 | X34: - | Y34: - | Z34: 28.89 | AA34: - | AB34: 28.89 | AC34: - | AD34: 0 | AE34: 28.89 | AF34: 28.89 | AG34: - | AH34: 962.85 | AI34: 28.89 | AJ34: - | AK34: - | AL34: 933.96
A35: 46254 | B35: 06:08 PM | C35: 45841 | F35: 124 | G35: - | H35: Hotel | I35: Almosafer | J35: - | K35: - | L35: - | M35: ba9ddbb3-5dc6-4694-bf6e-d9ea508c2973 | N35: Pending | O35: Pending | P35: Tamara | Q35: 226.45 | R35: - | S35: - | T35: - | U35: 0 | V35: 226.45 | W35: 226.45 | X35: - | Y35: - | Z35: 0 | AA35: 0 | AB35: 0 | AC35: - | AD35: 0 | AE35: 0 | AF35: 0 | AG35: 0 | AH35: 226.45 | AI35: 0 | AJ35: 0 | AK35: - | AL35: 226.45
A36: 46254 | B36: 05:27 PM | C36: 62725 | F36: 123 | G36: - | H36: Hotel | I36: Almosafer | J36: - | K36: - | L36: - | M36: - | N36: Expired | O36: - | P36: Card | Q36: 125.61 | R36: - | S36: - | T36: - | U36: 16.38 | V36: 125.61 | W36: 125.61 | X36: - | Y36: - | Z36: 0 | AA36: 0 | AB36: 0 | AC36: - | AD36: 0 | AE36: 0 | AF36: 0 | AG36: 0 | AH36: 125.61 | AI36: 0 | AJ36: 0 | AK36: - | AL36: 125.61
A37: 46254 | B37: 01:17 AM | C37: 64510 | F37: 122 | G37: - | H37: Hotel | I37: Almosafer | J37: - | K37: - | L37: - | M37: - | N37: Pending | O37: - | P37: Card | Q37: 7056.88 | R37: - | S37: - | T37: - | U37: 0 | V37: 7056.88 | W37: 7056.88 | X37: - | Y37: - | Z37: 0 | AA37: 0 | AB37: 0 | AC37: - | AD37: 0 | AE37: 0 | AF37: 0 | AG37: 0 | AH37: 7056.88 | AI37: 0 | AJ37: 0 | AK37: - | AL37: 7056.88
A38: 46253 | B38: 06:01 PM | C38: 51981 | D38: حسن فقيه | F38: 121 | G38: H260819107345500 | H38: Hotel | I38: Almosafer | J38: - | K38: - | L38: - | M38: tok_gxrunyib3gpyncel75lr6e7cgu | N38: Processed | O38: Completed | P38: Apple Pay | Q38: 1161.7 | R38: - | S38: - | T38: - | U38: 0 | V38: 1161.7 | W38: 1161.7 | X38: - | Y38: - | Z38: 0 | AA38: 1103.62 | AB38: 0 | AC38: - | AD38: 0 | AE38: 58.09 | AF38: 0 | AG38: 0 | AH38: 1161.7 | AI38: 58.09 | AJ38: 0 | AK38: - | AL38: 1103.61
A39: 46252 | B39: 05:11 PM | C39: 48424 | F39: 120 | G39: - | H39: Hotel | I39: Almosafer | J39: - | K39: - | L39: - | M39: - | N39: Expired | O39: - | P39: Card | Q39: 449 | R39: - | S39: - | T39: - | U39: 0 | V39: 449 | W39: 449 | X39: - | Y39: - | Z39: 0 | AA39: 0 | AB39: 0 | AC39: - | AD39: 0 | AE39: 0 | AF39: 0 | AG39: 0 | AH39: 449 | AI39: 0 | AJ39: 0 | AK39: - | AL39: 449

Sheet Analysis
A1: Order Date | B1: Order Time | C1: Customer | D1: Customer | E1: Customer | F1: SG Order ID | G1: Partner Order ID | H1: Vertical | I1: Provider Name | J1: Food Order Type | K1: Restaurant ID/Seller ID | L1: Restaurant Name | M1: Transaction ID | N1: Order Status | O1: Payment Status | P1: Payment Method | Q1: Sub Total | R1: Promocode | S1: SG Discount/Promo Amount | T1: SG Delivery Expense | U1: VAT | V1: Order Total | W1: Total Amount | X1: Vendor Delivery Expense | Y1: SG Comission % | Z1: Commission Amount | AA1: Partner Payout | AB1: Margin | AC1: Vendor Payment Term | AD1: SG Earnings (before VAT) | AE1: VAT on SG Earnings | AF1: SG Earning (including VAT) | AG1: Wallet Amount | AH1: Applepay/Card Amount | AI1: Commission Charged | AJ1: Refund Amount | AK1: Compensation Amount | AL1: Net Payable Amount to Partner | AM1: Match ID's | AN1: Com Rate Check | AO1: Vendor Rate Check | AP1: Difference | AQ1: Actual As Vendor | AR1: Net Payable | AS1: Customer ID | AT1: DOM/INT | AU1: Customer Name | AV1: Invoice Number | AW1: line Item | AX1: Billing Type | AY1: Issue Date | AZ1: Service Type | BA1: Service Provider | BB1: Service Reference | BC1: Description of Service | BD1: Supplier Name | BE1: Employee ID | BF1: Department | BG1: Entitlement | BH1: PNR No | BI1: Booking Date | BJ1: Check In Date | BK1: Check Out Date | BL1: Qty | BM1: No of Rooms | BN1: No of Nights | BO1: T/O Number | BP1: Client Name | BQ1: Route | BR1: Destination City | BS1: Class/Type | BT1: Total Price W.O VAT | BU1: VAT % | BV1: VAT | BW1: Airline Can Fee | BX1: Total Invoice Amount | BY1: commision amount | BZ1: net payable amount | CA1: Currency | CB1: Booking ID
A2: 46255 | B2: 06:22 PM | C2: 7435 | F2: 364 | G2: A26082185665500 | H2: Flights | I2: Almosafer | J2: - | K2: - | L2: - | M2: tok_gzzmucybmmvibgbnwp7b4xbppa | N2: Processed | O2: Paid | P2: Apple Pay | Q2: 935.12 | R2: - | S2: - | T2: - | U2: 121.97 | V2: 935.12 | W2: 935.12 | X2: - | Y2: - | Z2: 28.05 | AA2: - | AB2: 28.05 | AC2: - | AD2: 0 | AE2: 28.05 | AF2: 28.05 | AG2: - | AH2: 935.12 | AI2: 28.05 | AJ2: - | AK2: - | AL2: 907.07 | AM2: =G2=CC2 -> TRUE | AN2: =AI2/W2 -> 0.02999615 | AO2: =+BY2/BX2 -> 0.03000008 | AP2: =+AN2-AO2 -> -3.9299769e-06 | AQ2: =+AO2*W2 -> 28.053675 | AR2: =+W2-AQ2 -> 907.06633 | AS2: {=_xlfn.XLOOKUP(G2,'Vedor Report'!AK:AK,'Vedor Report'!A:AJ, "NA",0)} -> 2012559 | AT2: DOM | AU2: Qtoon Raqamya Trading Company | AV2: 2500054679 | AW2: 000001 | AX2: Invoice | AY2: 46255 | AZ2: A | BA2: F3 | BC2: E-Tckt-DS-ONL | BF2: QTOON RAQAMYA TRADING COMPANY | BH2: FB8Q9A | BI2: 46255 | BJ2: 09/04/2026 | BK2: 09/04/2026 | BL2: 1 | BO2: 000541882 | BP2: MS Jacqueline Ndayizeye MS S | BQ2: ABT-RUH | BS2: ECONOMY | BT2: 813.15 | BU2: 15 | BV2: 121.97 | BW2: 0 | BX2: 935.12 | BY2: 28.053675 | BZ2: 907.06633 | CA2: SAR | CB2: A26082185665500_7471325 | CC2: A26082185665500
A3: 46255 | B3: 01:34 AM | C3: 52652 | F3: 362 | G3: A260820198585500 | H3: Flights | I3: Almosafer | J3: - | K3: - | L3: - | M3: tok_w7c6oeabckky3p5j6ltbesrcdu | N3: Processed | O3: Paid | P3: Apple Pay + Wallet | Q3: 1408.1 | R3: - | S3: - | T3: - | U3: 183.67 | V3: 1408.1 | W3: 1408.1 | X3: - | Y3: - | Z3: 42.24 | AA3: - | AB3: 42.24 | AC3: - | AD3: 0 | AE3: 42.24 | AF3: 42.24 | AG3: 2 | AH3: 1406.1 | AI3: 42.24 | AJ3: - | AK3: - | AL3: 1365.86 | AM3: =G3=CC3 -> TRUE | AN3: =AI3/W3 -> 0.029997869 | AO3: =+BY3/BX3 -> 0.029999883 | AP3: =+AN3-AO3 -> -2.0133513e-06 | AQ3: =+AO3*W3 -> 42.242835 | AR3: =+W3-AQ3 -> 1365.8572 | AS3: {=_xlfn.XLOOKUP(G3,'Vedor Report'!AK:AK,'Vedor Report'!A:AJ, "NA",0)} -> 2012559 | AT3: DOM | AU3: Qtoon Raqamya Trading Company | AV3: 2500054678 | AW3: 000001 | AX3: Invoice | AY3: 46254 | AZ3: A | BA3: XY | BC3: E-Tckt-DS-ONL | BF3: QTOON RAQAMYA TRADING COMPANY | BH3: ZI84FX | BI3: 46254 | BJ3: 08/26/2026 | BK3: 08/30/2026 | BL3: 1 | BO3: 000541686 | BQ3: AJF-RUH-JED-RUH-AJF | BS3: ECONOMY | BT3: 1224.43 | BU3: 15 | BV3: 183.67 | BW3: 0 | BX3: 1408.1 | BY3: 42.242835 | BZ3: 1365.8572 | CA3: SAR | CB3: A260820198585500_841607 | CC3: A260820198585500
A4: 46253 | B4: 06:01 PM | C4: 51981 | D4: حسن فقيه | F4: 121 | G4: H260819107345500 | H4: Hotel | I4: Almosafer | J4: - | K4: - | L4: - | M4: tok_gxrunyib3gpyncel75lr6e7cgu | N4: Processed | O4: Completed | P4: Apple Pay | Q4: 1161.7 | R4: - | S4: - | T4: - | U4: 0 | V4: 1161.7 | W4: 1161.7 | X4: - | Y4: - | Z4: 0 | AA4: 1103.62 | AB4: 0 | AC4: - | AD4: 0 | AE4: 58.09 | AF4: 0 | AG4: 0 | AH4: 1161.7 | AI4: 58.09 | AJ4: 0 | AK4: - | AL4: 1103.61 | AM4: =G4=CC4 -> TRUE | AN4: =AI4/W4 -> 0.050004304 | AO4: =+BY4/BX4 -> 0.0575 | AP4: =+AN4-AO4 -> -0.007495696 | AQ4: =+AO4*W4 -> 66.79775 | AR4: =+W4-AQ4 -> 1094.9023 | AS4: {=_xlfn.XLOOKUP(G4,'Vedor Report'!AK:AK,'Vedor Report'!A:AJ, "NA",0)} -> 2012559 | AT4: INT | AU4: Qtoon Raqamya Trading Company | AV4: 2500054685 | AW4: 000001 | AX4: Invoice | AY4: 46253 | AZ4: H | BA4: HOTEL ORSO BRUNO | BB4: 2538409917 | BC4: Online-Accomodations | BD4: EXPEDIA | BF4: QTOON RAQAMYA TRADING COMPANY | BI4: 46253 | BJ4: 09/19/2026 | BK4: 09/20/2026 | BL4: 1 | BM4: 1 | BN4: 1 | BO4: H260819107345500 | BP4: Salah Faqihi | BR4: CARATE URIO | BS4: STANDARD ONE-BEDROOM ROOM - 2 | BT4: 1162.76 | BU4: 0 | BV4: 0 | BW4: 0 | BX4: 1162.76 | BY4: 66.8587 | BZ4: 1095.9013 | CA4: SAR | CB4: H260819107345500_3360174 | CC4: H260819107345500
A5: 46254 | B5: 04:41 PM | C5: 53917 | F5: 360 | G5: A26082095495500 | H5: Flights | I5: Almosafer | J5: - | K5: - | L5: - | M5: - | N5: Processed | O5: Paid | P5: Wallet | Q5: 754.27 | R5: - | S5: - | T5: - | U5: 0 | V5: 754.27 | W5: 754.27 | X5: - | Y5: - | Z5: 22.63 | AA5: - | AB5: 22.63 | AC5: - | AD5: 0 | AE5: 22.63 | AF5: 22.63 | AG5: 754.27 | AH5: - | AI5: 22.63 | AJ5: - | AK5: - | AL5: 731.64 | AM5: =G5=CC5 -> TRUE | AN5: =AI5/W5 -> 0.030002519 | AO5: =+BY5/BX5 -> 0.0345 | AP5: =+AN5-AO5 -> -0.004497481 | AQ5: =+AO5*W5 -> 26.022315 | AR5: =+W5-AQ5 -> 728.24768 | AS5: {=_xlfn.XLOOKUP(G5,'Vedor Report'!AK:AK,'Vedor Report'!A:AJ, "NA",0)} -> 2012559 | AT5: INT | AU5: Qtoon Raqamya Trading Company | AV5: 2500054677 | AW5: 000001 | AX5: Invoice | AY5: 46254 | AZ5: A | BA5: XY | BC5: E-Tckt-DS-ONL | BF5: QTOON RAQAMYA TRADING COMPANY | BH5: GICBFE | BI5: 46254 | BJ5: 08/30/2026 | BK5: 08/30/2026 | BL5: 1 | BO5: 000541488 | BP5: Baharithah Meshari | BQ5: RUH-BJV | BS5: ECONOMY | BT5: 754.27 | BU5: 0 | BV5: 0 | BW5: 0 | BX5: 754.27 | BY5: 26.022315 | BZ5: 728.24768 | CA5: SAR | CB5: A26082095495500_8209175 | CC5: A26082095495500
A6: 46251 | B6: 10:28 PM | C6: 54062 | F6: 344 | G6: A260817163765500 | H6: Flights | I6: Almosafer | J6: - | K6: - | L6: - | M6: tok_g5vf2sibjwvi5pjmeasnbhqqkq | N6: Processed | O6: Paid | P6: Apple Pay | Q6: 442.04 | R6: - | S6: - | T6: - | U6: 57.66 | V6: 442.04 | W6: 442.04 | X6: - | Y6: - | Z6: 13.26 | AA6: - | AB6: 13.26 | AC6: - | AD6: 0 | AE6: 13.26 | AF6: 13.26 | AG6: - | AH6: 442.04 | AI6: 13.26 | AJ6: - | AK6: - | AL6: 428.78 | AM6: =G6=CC6 -> TRUE | AN6: =AI6/W6 -> 0.029997285 | AO6: =+BY6/BX6 -> 0.029999796 | AP6: =+AN6-AO6 -> -2.511085e-06 | AQ6: =+AO6*W6 -> 13.26111 | AR6: =+W6-AQ6 -> 428.77889 | AS6: {=_xlfn.XLOOKUP(G6,'Vedor Report'!AK:AK,'Vedor Report'!A:AJ, "NA",0)} -> 2012559 | AT6: DOM | AU6: Qtoon Raqamya Trading Company | AV6: 2500054676 | AW6: 000001 | AX6: Invoice | AY6: 46251 | AZ6: A | BA6: F3 | BC6: E-Tckt-DS-ONL | BF6: QTOON RAQAMYA TRADING COMPANY | BH6: W6S2MS | BI6: 46251 | BJ6: 08/23/2026 | BK6: 08/23/2026 | BL6: 1 | BO6: 000539882 | BP6: MR Abdullah Aloufi | BQ6: AHB-JED | BS6: ECONOMY | BT6: 384.38 | BU6: 15 | BV6: 57.66 | BW6: 0 | BX6: 442.04 | BY6: 13.26111 | BZ6: 428.77889 | CA6: SAR | CB6: A260817163765500_865574 | CC6: A260817163765500
A7: 46251 | B7: 02:08 PM | C7: 22 | D7: ss alsalloom | F7: 342 | G7: A26081760435500 | H7: Flights | I7: Almosafer | J7: - | K7: - | L7: - | M7: pay_xtpephabc4lidld5agyqqyr2pq | N7: Processed | O7: Paid | P7: Card + Wallet | Q7: 1324.08 | R7: - | S7: - | T7: - | U7: 0 | V7: 1324.08 | W7: 1324.08 | X7: - | Y7: - | Z7: 39.72 | AA7: - | AB7: 39.72 | AC7: - | AD7: 0 | AE7: 39.72 | AF7: 39.72 | AG7: 30 | AH7: 1294.08 | AI7: 39.72 | AJ7: - | AK7: - | AL7: 1284.36 | AM7: =G7=CC7 -> TRUE | AN7: =AI7/W7 -> 0.029998187 | AO7: =+BY7/BX7 -> 0.0345 | AP7: =+AN7-AO7 -> -0.0045018126 | AQ7: =+AO7*W7 -> 45.68076 | AR7: =+W7-AQ7 -> 1278.3992 | AS7: {=_xlfn.XLOOKUP(G7,'Vedor Report'!AK:AK,'Vedor Report'!A:AJ, "NA",0)} -> 2012559 | AT7: INT | AU7: Qtoon Raqamya Trading Company | AV7: 2500054633 | AW7: 000001 | AX7: Invoice | AY7: 46251 | AZ7: A | BA7: RJ | BB7: 4861440457 | BC7: E-Tckt-DS-ONL | BF7: QTOON RAQAMYA TRADING COMPANY | BH7: 7IDXN4 | BI7: 46251 | BJ7: 08/17/2026 | BK7: 08/17/2026 | BL7: 1 | BO7: 000539591 | BP7: HUSAIN ALI | BQ7: AMM-DMM | BS7: Q | BT7: 1324.08 | BU7: 0 | BV7: 0 | BW7: 0 | BX7: 1324.08 | BY7: 45.68076 | BZ7: 1278.3992 | CA7: SAR | CB7: A26081760435500_4482019 | CC7: A26081760435500
A8: 46247 | B8: 06:06 PM | C8: 8003 | D8: mahendra Asar | F8: 300 | G8: A260813120395500 | H8: Flights | I8: Almosafer | J8: - | K8: - | L8: - | M8: pay_grvzqoqbatfivhp37pnye2qkri | N8: Processed | O8: Paid | P8: Card + Wallet | Q8: 958.79 | R8: - | S8: - | T8: - | U8: 0 | V8: 958.79 | W8: 958.79 | X8: - | Y8: - | Z8: 28.76 | AA8: - | AB8: 28.76 | AC8: - | AD8: 0 | AE8: 28.76 | AF8: 28.76 | AG8: 477.15 | AH8: 481.64 | AI8: 28.76 | AJ8: - | AK8: - | AL8: 930.03 | AM8: =G8=CC8 -> TRUE | AN8: =AI8/W8 -> 0.029996141 | AO8: =+BY8/BX8 -> 0.0345 | AP8: =+AN8-AO8 -> -0.004503859 | AQ8: =+AO8*W8 -> 33.078255 | AR8: =+W8-AQ8 -> 925.71174 | AS8: {=_xlfn.XLOOKUP(G8,'Vedor Report'!AK:AK,'Vedor Report'!A:AJ, "NA",0)} -> 2012559 | AT8: INT | AU8: Qtoon Raqamya Trading Company | AV8: 2500054717 | AW8: 000001 | AX8: Invoice | AY8: 46256 | AZ8: A | BA8: FZ | BC8: E-Tckt-DS-ONL | BF8: QTOON RAQAMYA TRADING COMPANY | BH8: 7IGW84 | BI8: 46247 | BJ8: 08/14/2026 | BK8: 08/14/2026 | BL8: 1 | BO8: 000537832 | BP8: MAHENDRA ASARPOTA | BQ8: RUH-DXB | BS8: ECONOMY | BT8: 481.38 | BU8: 0 | BV8: 0 | BW8: 0 | BX8: 481.38 | BY8: 16.60761 | BZ8: 464.77239 | CA8: SAR | CB8: A260813120395500_5944762 | CC8: A260813120395500
A9: 46247 | B9: 06:06 PM | C9: 8003 | D9: mahendra Asar | F9: 299 | G9: A260813120395500-1 | AM9: Repeat | AS9: {=_xlfn.XLOOKUP(G9,'Vedor Report'!AK:AK,'Vedor Report'!A:AJ, "NA",0)} -> 2012559 | AT9: INT | AU9: Qtoon Raqamya Trading Company | AV9: 2500054717 | AW9: 000002 | AX9: Invoice | AY9: 46256 | AZ9: A | BA9: XY | BC9: E-Tckt-DS-ONL | BF9: QTOON RAQAMYA TRADING COMPANY | BH9: J7G92V | BI9: 46247 | BJ9: 08/17/2026 | BK9: 08/17/2026 | BL9: 1 | BO9: 000537832 | BP9: Asarpota Mahendra | BQ9: DXB-RUH | BS9: ECONOMY | BT9: 477.41 | BU9: 0 | BV9: 0 | BW9: 0 | BX9: 477.41 | BY9: 16.470645 | BZ9: 460.93936 | CA9: SAR | CB9: A260813120395500_5944762 | CC9: A260813120395500-1
AR10: =SUM(AR2:AR9) -> 6728.9633
BW11: SG | BX11: Vendor | BY11: Difference | BZ11: =SUM(BZ2:BZ9) -> 6729.9624
BV12: H260819107345500 | BW12: =+W4 -> 1161.7 | BX12: =+BT4 -> 1162.76 | BZ12: =+BW12-BX12 -> -1.06
BZ13: =+BZ11+BZ12 -> 6728.9024
AP16: 6984.1 | AQ16: 255.14 | AR16: =+AP16-AQ16 -> 6728.96
AP21: Summary | AQ21: SG Records | AR21: Vendor Report | AS21: Total Difference
AP22: Claim 09 To 15 August | AQ22: 9032.569 | AR22: 9036.2071 | AS22: =+AQ22-AR22 -> -3.63805
AP23: Claim 16 To 22 August | AQ23: =+AR10 -> 6728.9633 | AR23: 6729.9623 | AS23: =+AQ23-AR23 -> -0.99905
AQ24: =+AQ22+AQ23 -> 15761.532 | AR24: =SUM(AR22:AR23) -> 15766.169 | AS24: =+AQ24-AR24 -> -4.6371
AP26: Claim 09 To 15 August | AQ26: Hotel | AR26: 116.5 | AS26: =+AR26/1.15 -> 101.30435
AQ27: flig | AR27: 248.76 | AS27: =+AR27/1.15 -> 216.31304
AP28: Claim 16 To 22 August | AQ28: Hotel | AR28: 66.8 | AS28: =+AR28/1.15 -> 58.086957
AQ29: flig | AR29: 188.34 | AS29: =+AR29/1.15 -> 163.77391
AR30: =SUM(AR26:AR29) -> 620.4 | AS30: =SUM(AS26:AS29) -> 539.47826
T34: 935.12 | U34: 935.12 | V34: =+T34-U34 -> 0
T35: 1408.1 | U35: 1408.1 | V35: =+T35-U35 -> 0
T36: 1161.7 | U36: 1162.76 | V36: =+T36-U36 -> -1.06
T37: 754.27 | U37: 754.27 | V37: =+T37-U37 -> 0
T38: 442.04 | U38: 442.04 | V38: =+T38-U38 -> 0
T39: 1324.08 | U39: 1324.08 | V39: =+T39-U39 -> 0 | AT39: -66.82 | AU39: =+AT39/1.15 -> -58.104348
T40: 958.79 | U40: 481.38 | V40: =+T40-U40-U41 -> 0
U41: 477.41

Sheet Sheet1
C8: SHOPPINGGATE | H8: ALMOSAFIR | M8: DIFFERENCE
B9: CLAIM PERIOD | C9: Booking ID | D9: Base Amount (TOTAL) | E9: COM AMOUNT | F9: Net Payable | H9: Booking ID | I9: Base Amount (TOTAL) | J9: COM AMOUNT | K9: Net Payable | M9: Base Amount (TOTAL) | N9: COM AMOUNT | O9: Net Payable
B10: Claim 16 to 22 August 2026 | C10: H260819107345500 | D10: 1161.7 | E10: =+D10*0.0575 -> 66.79775 | F10: =+D10-E10 -> 1094.9023 | H10: H260819107345500_3360174 | I10: 1162.76 | J10: =+I10*0.0575 -> 66.8587 | K10: =I10-J10 -> 1095.9013 | M10: =+D10-I10 -> -1.06 | N10: =+E10-J10 -> -0.06095 | O10: =+F10-K10 -> -0.99905
B11: Claim 09 to 15 August 2026 | C11: H260809147315500 | D11: 758.31 | E11: =+D11*0.0575 -> 43.602825 | F11: =+D11-E11 -> 714.70718 | H11: H260809147315500_5278069 | I11: 760.42 | J11: 43.72415 | K11: 716.69585 | M11: =+D11-I11 -> -2.11 | N11: =+E11-J11 -> -0.121325 | O11: =+F11-K11 -> -1.988675
B12: Claim 09 to 15 August 2026 | C12: H26081419825500 | D12: 604.44 | E12: =+D12*0.0575 -> 34.7553 | F12: =+D12-E12 -> 569.6847 | H12: H26081419825500_7480138 | I12: 606.25 | J12: =+I12*0.0575 -> 34.859375 | K12: =I12-J12 -> 571.39062 | M12: =+D12-I12 -> -1.81 | N12: =+E12-J12 -> -0.104075 | O12: =+F12-K12 -> -1.705925
D13: =SUM(D10:D12) -> 2524.45 | E13: =SUM(E10:E12) -> 145.15588 | F13: =SUM(F10:F12) -> 2379.2941 | I13: =SUM(I10:I12) -> 2529.43 | J13: =SUM(J10:J12) -> 145.44223 | K13: =SUM(K10:K12) -> 2383.9878 | M13: =+D13-I13 -> -4.98 | N13: =+E13-J13 -> -0.28635 | O13: =+F13-K13 -> -4.69365
D22: Claim 16 to 22 August 2026 | E22: 9334.87 | F22: 298.66771 | G22: 9036.2023
D23: Claim 09 to 15 August 2026 | E23: 6985.16 | F23: 255.19765 | G23: 6729.9623
D24: TOTAL CLAIMED AMOUNT | E24: =SUM(E22:E23) -> 16320.03 | F24: =SUM(F22:F23) -> 553.86536 | G24: =SUM(G22:G23) -> 15766.165
D25: Diffrence | E25: =+M13 -> -4.98 | F25: =+N13 -> -0.28635 | G25: =+O13 -> -4.69365
D26: Total Amount | E26: =+E24+E25 -> 16315.05 | F26: =+F24+F25 -> 553.57901 | G26: =+G24+G25 -> 15761.471
